[
  {
    "id": "hero",
    "description": "Elegant fashion runway show with diverse models",
    "imageUrl": "https://picsum.photos/seed/fashionrunway/1920/1080",
    "imageHint": "fashion runway"
  },
  {
    "id": "academy-hero",
    "description": "Professional high-end fashion design atelier with mannequins and fabric",
    "imageUrl": "https://picsum.photos/seed/luxuryatelier/1920/1080",
    "imageHint": "fashion atelier studio"
  },
  {
    "id": "product-1",
    "description": "Woman in a royal blue and gold Adire silk kaftan",
    "imageUrl": "https://picsum.photos/seed/kaftan1/800/1000",
    "imageHint": "adire kaftan"
  },
  {
    "id": "product-2",
    "description": "Woman in a grand, hand-woven Aso-Oke boubou for a wedding",
    "imageUrl": "https://picsum.photos/seed/asooke2/800/1000",
    "imageHint": "aso oke"
  },
  {
    "id": "product-3",
    "description": "Man wearing a white, intricately embroidered Agbada set",
    "imageUrl": "https://picsum.photos/seed/agbada3/800/1000",
    "imageHint": "agbada"
  },
  {
    "id": "product-4",
    "description": "Woman in a modern pink lace Iro and Buba set",
    "imageUrl": "https://picsum.photos/seed/irobuba4/800/1000",
    "imageHint": "iro buba"
  },
  {
    "id": "product-5",
    "description": "Woman smiling in a colorful Ankara print peplum top",
    "imageUrl": "https://picsum.photos/seed/ankara5/800/1000",
    "imageHint": "ankara top"
  },
  {
    "id": "product-6",
    "description": "Woman in a vibrant, flared Ankara midi dress",
    "imageUrl": "https://picsum.photos/seed/ankaradress6/800/1000",
    "imageHint": "ankara dress"
  },
  {
    "id": "product-7",
    "description": "Man in a black velvet Isiagu tunic with gold lion head embroidery",
    "imageUrl": "https://picsum.photos/seed/isiagu7/800/1000",
    "imageHint": "isiagu tunic"
  },
  {
    "id": "product-8",
    "description": "Close-up of a traditional Nigerian coral bead necklace set",
    "imageUrl": "https://picsum.photos/seed/beads8/800/1000",
    "imageHint": "coral beads"
  },
  {
    "id": "product-9",
    "description": "Woman wearing an elegant, pre-styled golden Auto Gele",
    "imageUrl": "https://picsum.photos/seed/gele9/800/1000",
    "imageHint": "gele headtie"
  },
  {
    "id": "product-10",
    "description": "Man in a sharp, tailored navy blue Senator style suit",
    "imageUrl": "https://picsum.photos/seed/senator10/800/1000",
    "imageHint": "senator suit"
  },
  {
    "id": "product-11",
    "description": "Woman wearing stylish, high-waisted Ankara wide-leg trousers",
    "imageUrl": "https://picsum.photos/seed/trousers11/800/1000",
    "imageHint": "ankara trousers"
  },
  {
    "id": "product-12",
    "description": "Woman in a glamorous off-shoulder Buba gown in emerald green",
    "imageUrl": "https://picsum.photos/seed/gown12/800/1000",
    "imageHint": "buba gown"
  },
  {
    "id": "product-13",
    "description": "Stunning sequin-embellished Aso Ebi gown in champagne gold",
    "imageUrl": "https://picsum.photos/seed/asoebi13/800/1000",
    "imageHint": "sequin gown"
  },
  {
    "id": "product-14",
    "description": "Man wearing a classic Dashiki shirt with an intricate pattern",
    "imageUrl": "https://picsum.photos/seed/dashiki14/800/1000",
    "imageHint": "dashiki shirt"
  },
  {
    "id": "course-1",
    "description": "Designer sketching a fashion illustration with colored markers",
    "imageUrl": "https://picsum.photos/seed/illustration1/800/600",
    "imageHint": "fashion illustration"
  },
  {
    "id": "course-2",
    "description": "Fabric being draped on a mannequin in a design studio",
    "imageUrl": "https://picsum.photos/seed/draping2/800/600",
    "imageHint": "fashion draping"
  },
  {
    "id": "course-3",
    "description": "Close-up of a tablet screen showing digital fashion design software",
    "imageUrl": "https://picsum.photos/seed/digital3/800/600",
    "imageHint": "digital design"
  },
  {
    "id": "course-4",
    "description": "A fashion mood board with photos, sketches, and fabric swatches",
    "imageUrl": "https://picsum.photos/seed/moodboard4/800/600",
    "imageHint": "fashion business"
  },
  {
    "id": "course-5",
    "description": "A student using Procreate on an iPad to design clothing",
    "imageUrl": "https://picsum.photos/seed/procreate5/800/600",
    "imageHint": "digital design"
  },
  {
    "id": "course-6",
    "description": "A well-organized fashion business workspace with laptops and samples",
    "imageUrl": "https://picsum.photos/seed/workspace6/800/600",
    "imageHint": "fashion business"
  },
  {
    "id": "avatar-1",
    "description": "Portrait of a friendly and creative female fashion instructor",
    "imageUrl": "https://picsum.photos/seed/woman1/400/400",
    "imageHint": "woman portrait"
  },
  {
    "id": "avatar-2",
    "description": "Portrait of a professional and stylish male fashion instructor",
    "imageUrl": "https://picsum.photos/seed/man2/400/400",
    "imageHint": "man portrait"
  }
]